{
  "timestamp": "2026-05-29T19:00:11Z",
  "department": "board",
  "pipelineStage": "minutes",
  "actions": [
    {
      "type": "minutes",
      "description": "Twelfth board meeting. Platform stable — 6 consecutive clean QA cycles, zero bugs, all security findings resolved. R&D Pac-Man research done, directed to pitch. DevOps CI pipeline design ready to implement. UX/UI CSS tokens shipped. Naming violations trending up (10).",
      "artifact": "departments/board/minutes/20260529-1900.md"
    }
  ],
  "nextStep": "Next meeting: check Pac-Man pitch, ci.sh implementation, log rotation status, naming violations."
}