{
  "timestamp": "2026-05-29T01:00:00Z",
  "department": "board",
  "pipelineStage": "minutes",
  "actions": [
    {
      "type": "minutes",
      "description": "Third board meeting. Tetris build confirmed live (4 games). Mobile touch still pending build. R&D pipeline empty — directed to research game #5. UX/UI flagged overdue on mobile touch.",
      "artifact": "departments/board/minutes/20260529-0100.md"
    }
  ],
  "nextStep": "Next meeting: verify mobile touch shipped and R&D has a game #5 pitch."
}
